{"stationId":8,"datetime":"2021-07-16T10:50:00+03:00","channel":"Rain","value":0.0}
{"stationId":8,"datetime":"2021-07-16T11:20:00+03:00","channel":"Rain","value":1.0}
{"stationId":8,"datetime":"2021-07-16T11:50:00+03:00","channel":"Rain","value":2.0}
{"stationId":8,"datetime":"2021-07-16T12:20:00+03:00","channel":"Rain","value":3.0}
{"stationId":8,"datetime":"2021-07-16T12:50:00+03:00","channel":"Rain","value":4.0}
{"stationId":8,"datetime":"2021-07-16T13:20:00+03:00","channel":"Rain","value":5.0}
{"stationId":8,"datetime":"2021-07-16T13:50:00+03:00","channel":"Rain","value":6.0}
{"stationId":8,"datetime":"2021-07-16T14:20:00+03:00","channel":"Rain","value":7.0}
{"stationId":8,"datetime":"2021-07-16T14:50:00+03:00","channel":"Rain","value":8.0}
{"stationId":8,"datetime":"2021-07-16T15:20:00+03:00","channel":"Rain","value":9.0}
{"stationId":8,"datetime":"2021-07-16T15:50:00+03:00","channel":"Rain","value":10.0}
{"stationId":8,"datetime":"2021-07-16T16:20:00+03:00","channel":"Rain","value":11.0}

